rust_rcon/__init__.py
rust_rcon/command.py
rust_rcon/wsclient.py
rust_rcon-0.0.3.dist-info/LICENSE
rust_rcon-0.0.3.dist-info/METADATA
rust_rcon-0.0.3.dist-info/WHEEL
rust_rcon-0.0.3.dist-info/top_level.txt
rust_rcon-0.0.3.dist-info/RECORD
