Metadata-Version: 2.1
Name: rust-rcon
Version: 0.0.3
Summary: Simple utility for interfacing with rust's rcon implementation
Home-page: https://github.com/samdixon/rust-rcon
Author: Samuel Dixon
Author-email: sdixon@posteo.net
License: MIT
Platform: UNKNOWN
Classifier: License :: OSI Approved :: MIT License
Classifier: Programming Language :: Python
Classifier: Programming Language :: Python :: 3
Classifier: Programming Language :: Python :: 3.6
Classifier: Programming Language :: Python :: Implementation :: CPython
Classifier: Programming Language :: Python :: Implementation :: PyPy
Requires-Python: >=3.6.0
Requires-Dist: websocket-client
Provides-Extra: dev
Requires-Dist: pytest ; extra == 'dev'
Requires-Dist: neovim ; extra == 'dev'
